anotiai_pii_masker/__init__.py
anotiai_pii_masker/guardian.py
anotiai_pii_masker/Classification/__init__.py
anotiai_pii_masker/Classification/config.py
anotiai_pii_masker/Classification/dataset.py
anotiai_pii_masker/Classification/evaluate.py
anotiai_pii_masker/Classification/inference.py
anotiai_pii_masker/Classification/inference_baseline.py
anotiai_pii_masker/Classification/model.py
anotiai_pii_masker/Classification/predict.py
anotiai_pii_masker/Classification/train.py
anotiai_pii_masker/Classification/train_baseline.py
anotiai_pii_masker/Classification/tune.py
anotiai_pii_masker/client/__init__.py
anotiai_pii_masker/client/api_client.py
anotiai_pii_masker/client/config.py
anotiai_pii_masker/client/exceptions.py
anotiai_pii_masker/extraction_engine/__init__.py
anotiai_pii_masker/extraction_engine/presidio_pii/__init__.py
anotiai_pii_masker/extraction_engine/presidio_pii/detector.py
anotiai_pii_masker/extraction_engine/presidio_pii/evaluate.py
anotiai_pii_masker/extraction_engine/presidio_pii/recognizers.py
anotiai_pii_masker/extraction_engine/presidio_pii/utils.py
anotiai_pii_masker/extraction_engine/qa_pii/__init__.py
anotiai_pii_masker/extraction_engine/qa_pii/detector.py
anotiai_pii_masker/extraction_engine/qa_pii/questions.py
anotiai_pii_masker/extraction_engine/spacy_pii/__init__.py
anotiai_pii_masker/extraction_engine/spacy_pii/detector.py
anotiai_pii_masker/extraction_engine/spacy_pii/evaluate.py
anotiai_pii_masker/extraction_engine/spacy_pii/utils.py
anotiai_pii_masker/extraction_engine/spacy_pii/validators.py
anotiai_pii_masker-2.0.0.dist-info/licenses/LICENSE
anotiai_pii_masker-2.0.0.dist-info/METADATA
anotiai_pii_masker-2.0.0.dist-info/WHEEL
anotiai_pii_masker-2.0.0.dist-info/top_level.txt
anotiai_pii_masker-2.0.0.dist-info/RECORD
