Metadata-Version: 2.4
Name: anotiai-pii-masker
Version: 2.0.0
Summary: Cloud-powered PII detection and masking with local fallback support.
Author-email: Emmanuel <emmanuel@anotiai.com>
Project-URL: Homepage, https://github.com/anotiai/anotiai-pii-masker
Project-URL: Documentation, https://github.com/anotiai/anotiai-pii-masker#readme
Project-URL: Repository, https://github.com/anotiai/anotiai-pii-masker
Project-URL: Issues, https://github.com/anotiai/anotiai-pii-masker/issues
Keywords: pii,privacy,data-protection,nlp,machine-learning,cloud-ai
Classifier: Programming Language :: Python :: 3
Classifier: License :: OSI Approved :: MIT License
Classifier: Operating System :: OS Independent
Classifier: Topic :: Scientific/Engineering :: Artificial Intelligence
Classifier: Topic :: Security
Classifier: Topic :: Text Processing :: Linguistic
Requires-Python: >=3.8
License-File: LICENSE
Requires-Dist: requests>=2.28.0
Requires-Dist: pydantic>=2.0.0
Requires-Dist: python-jose>=3.0.0
Requires-Dist: pandas>=1.5.0
Provides-Extra: local
Requires-Dist: torch>=2.0.0; extra == "local"
Requires-Dist: transformers>=4.21.0; extra == "local"
Requires-Dist: scikit-learn>=1.1.0; extra == "local"
Requires-Dist: numpy>=1.21.0; extra == "local"
Requires-Dist: sentencepiece; extra == "local"
Requires-Dist: tiktoken; extra == "local"
Requires-Dist: presidio-analyzer>=2.2.33; extra == "local"
Requires-Dist: presidio-anonymizer>=2.2.33; extra == "local"
Requires-Dist: spacy>=3.4.0; extra == "local"
Requires-Dist: phonenumbers>=8.12.0; extra == "local"
Provides-Extra: cloud
Requires-Dist: requests>=2.28.0; extra == "cloud"
Requires-Dist: urllib3>=1.26.0; extra == "cloud"
Provides-Extra: dev
Requires-Dist: pytest>=7.0.0; extra == "dev"
Requires-Dist: pytest-cov>=4.0.0; extra == "dev"
Requires-Dist: black>=22.0.0; extra == "dev"
Requires-Dist: flake8>=5.0.0; extra == "dev"
Requires-Dist: mypy>=1.0.0; extra == "dev"
Requires-Dist: pre-commit>=2.20.0; extra == "dev"
Provides-Extra: all
Requires-Dist: torch>=2.0.0; extra == "all"
Requires-Dist: transformers>=4.21.0; extra == "all"
Requires-Dist: scikit-learn>=1.1.0; extra == "all"
Requires-Dist: numpy>=1.21.0; extra == "all"
Requires-Dist: sentencepiece; extra == "all"
Requires-Dist: tiktoken; extra == "all"
Requires-Dist: presidio-analyzer>=2.2.33; extra == "all"
Requires-Dist: presidio-anonymizer>=2.2.33; extra == "all"
Requires-Dist: spacy>=3.4.0; extra == "all"
Requires-Dist: phonenumbers>=8.12.0; extra == "all"
Requires-Dist: requests>=2.28.0; extra == "all"
Requires-Dist: urllib3>=1.26.0; extra == "all"
Dynamic: license-file
